MANIFEST.in
README.rst
setup.py
docs/HISTORY.rst
docs/INSTALL.txt
docs/LICENSE.GPL
docs/LICENSE.txt
docs/pas.plugins.proxy-0.1.0-01.png
pas/__init__.py
pas.plugins.proxy.egg-info/PKG-INFO
pas.plugins.proxy.egg-info/SOURCES.txt
pas.plugins.proxy.egg-info/dependency_links.txt
pas.plugins.proxy.egg-info/entry_points.txt
pas.plugins.proxy.egg-info/namespace_packages.txt
pas.plugins.proxy.egg-info/not-zip-safe
pas.plugins.proxy.egg-info/requires.txt
pas.plugins.proxy.egg-info/top_level.txt
pas/plugins/__init__.py
pas/plugins/proxy/__init__.py
pas/plugins/proxy/addform.pt
pas/plugins/proxy/config.py
pas/plugins/proxy/configure.zcml
pas/plugins/proxy/custom_fields.py
pas/plugins/proxy/i18n.sh
pas/plugins/proxy/interfaces.py
pas/plugins/proxy/plugin.py
pas/plugins/proxy/setuphandlers.py
pas/plugins/proxy/testing.py
pas/plugins/proxy/vocabularies.py
pas/plugins/proxy/Extensions/install.py
pas/plugins/proxy/browser/__init__.py
pas/plugins/proxy/browser/configure.zcml
pas/plugins/proxy/browser/controlpanel.pt
pas/plugins/proxy/browser/controlpanel.py
pas/plugins/proxy/browser/static/pas_proxy.css
pas/plugins/proxy/browser/static/proxy.png
pas/plugins/proxy/locales/pas.plugins.proxy-manual.pot
pas/plugins/proxy/locales/pas.plugins.proxy.pot
pas/plugins/proxy/locales/it/LC_MESSAGES/pas.plugins.proxy.mo
pas/plugins/proxy/locales/it/LC_MESSAGES/pas.plugins.proxy.po
pas/plugins/proxy/profiles/default/browserlayer.xml
pas/plugins/proxy/profiles/default/controlpanel.xml
pas/plugins/proxy/profiles/default/cssregistry.xml
pas/plugins/proxy/profiles/default/metadata.xml
pas/plugins/proxy/profiles/default/pas.plugins.proxy-various.txt
pas/plugins/proxy/profiles/default/registry.xml
pas/plugins/proxy/profiles/default/rolemap.xml
pas/plugins/proxy/profiles/test/rolemap.xml
pas/plugins/proxy/profiles/test/sharing.xml
pas/plugins/proxy/profiles/uninstall/browserlayer.xml
pas/plugins/proxy/profiles/uninstall/controlpanel.xml
pas/plugins/proxy/profiles/uninstall/cssregistry.xml
pas/plugins/proxy/profiles/uninstall/registry.xml
pas/plugins/proxy/tests/__init__.py
pas/plugins/proxy/tests/base.py
pas/plugins/proxy/tests/test_globalroles_plugin.py
pas/plugins/proxy/tests/test_groups_plugin.py
pas/plugins/proxy/tests/test_localroles_plugin.py