Metadata-Version: 1.0
Name: pas.plugins.proxy
Version: 0.1.0
Summary: A Plone PAS plugin for proxy roles between users
Home-page: https://github.com/RedTurtle/pas.plugins.proxy
Author: RedTurtle Technology
Author-email: sviluppoplone@redturtle.it
License: GPL
Keywords: pas plugin proxy
Platform: UNKNOWN
Classifier: Framework :: Plone
Classifier: Framework :: Plone :: 4.3
Classifier: Programming Language :: Python
